reviewhound/__init__.py
reviewhound/__main__.py
reviewhound/cli.py
reviewhound/common.py
reviewhound/config.py
reviewhound/database.py
reviewhound/models.py
reviewhound/scheduler.py
reviewhound/services.py
reviewhound/alerts/__init__.py
reviewhound/alerts/email.py
reviewhound/analysis/__init__.py
reviewhound/analysis/sentiment.py
reviewhound/scrapers/__init__.py
reviewhound/scrapers/base.py
reviewhound/scrapers/bbb.py
reviewhound/scrapers/google_places.py
reviewhound/scrapers/trustpilot.py
reviewhound/scrapers/yelp.py
reviewhound/scrapers/yelp_api.py
reviewhound/tui/__init__.py
reviewhound/tui/app.py
reviewhound/tui/services/__init__.py
reviewhound/tui/services/docker.py
reviewhound/tui/services/health.py
reviewhound/tui/services/process.py
reviewhound/tui/widgets/__init__.py
reviewhound/tui/widgets/commands.py
reviewhound/tui/widgets/config.py
reviewhound/tui/widgets/logs.py
reviewhound/tui/widgets/services.py
reviewhound/tui/widgets/sidebar.py
reviewhound/web/__init__.py
reviewhound/web/app.py
reviewhound/web/routes.py
reviewhound/web/static/style.css
reviewhound/web/templates/base.html
reviewhound/web/templates/business.html
reviewhound/web/templates/dashboard.html
reviewhound/web/templates/reviews.html
reviewhound/web/templates/settings.html
reviewhound/web/templates/welcome.html
reviewhound-1.0.0.dist-info/licenses/LICENSE
reviewhound-1.0.0.dist-info/METADATA
reviewhound-1.0.0.dist-info/WHEEL
reviewhound-1.0.0.dist-info/entry_points.txt
reviewhound-1.0.0.dist-info/top_level.txt
reviewhound-1.0.0.dist-info/RECORD
