Metadata-Version: 2.4
Name: reviewhound
Version: 1.0.0
Summary: Business review aggregator and monitoring tool with sentiment analysis
License-Expression: MIT
Project-URL: Homepage, https://github.com/jonmartin721/review-hound
Project-URL: Repository, https://github.com/jonmartin721/review-hound
Project-URL: Bug Tracker, https://github.com/jonmartin721/review-hound/issues
Keywords: reviews,scraping,sentiment-analysis,business,monitoring,trustpilot,yelp,bbb
Classifier: Development Status :: 5 - Production/Stable
Classifier: Environment :: Console
Classifier: Environment :: Web Environment
Classifier: Intended Audience :: Developers
Classifier: Operating System :: OS Independent
Classifier: Programming Language :: Python :: 3
Classifier: Programming Language :: Python :: 3.11
Classifier: Programming Language :: Python :: 3.12
Classifier: Topic :: Internet :: WWW/HTTP :: Dynamic Content
Requires-Python: >=3.11
License-File: LICENSE
Requires-Dist: beautifulsoup4>=4.12.0
Requires-Dist: requests>=2.31.0
Requires-Dist: sqlalchemy>=2.0.0
Requires-Dist: textblob>=0.18.0
Requires-Dist: flask>=3.0.0
Requires-Dist: apscheduler>=3.10.0
Requires-Dist: click>=8.1.0
Requires-Dist: rich>=13.0.0
Requires-Dist: python-dotenv>=1.0.0
Requires-Dist: textual>=0.40.0
Requires-Dist: playwright>=1.40.0
Provides-Extra: dev
Requires-Dist: pytest>=8.0.0; extra == "dev"
Requires-Dist: pytest-cov>=4.0.0; extra == "dev"
Requires-Dist: responses>=0.25.0; extra == "dev"
Requires-Dist: build; extra == "dev"
Requires-Dist: twine; extra == "dev"
Dynamic: license-file
